README.md
setup.cfg
setup.py
example/__init__.py
example/appengine_oauth.py
example/client.py
example/server.py
oauth10a/__init__.py
oauth10a/_compat.py
oauth10a/_version.py
oauth10a.egg-info/PKG-INFO
oauth10a.egg-info/SOURCES.txt
oauth10a.egg-info/dependency_links.txt
oauth10a.egg-info/requires.txt
oauth10a.egg-info/top_level.txt
oauth10a.egg-info/zip-safe
oauth10a/clients/__init__.py
oauth10a/clients/imap.py
oauth10a/clients/smtp.py