Metadata-Version: 1.1
Name: oauth10a
Version: 1.9.1
Summary: library for OAuth 1.0a
Home-page: https://github.com/TimSC/python-oauth10a
Author: Tim Sheerman-Chase
Author-email: orders2008@sheerman-chase.org.uk
License: MIT License
Keywords: oauth
Platform: UNKNOWN
Classifier: Intended Audience :: Developers
Classifier: Programming Language :: Python :: 2
Classifier: Programming Language :: Python :: 2.6
Classifier: Programming Language :: Python :: 2.7
Classifier: Programming Language :: Python :: 3
Classifier: Programming Language :: Python :: 3.3
Classifier: Programming Language :: Python :: 3.4
Classifier: Programming Language :: Python :: Implementation :: CPython
Classifier: Development Status :: 5 - Production/Stable
Classifier: Natural Language :: English
Classifier: License :: OSI Approved :: MIT License
